aiodi/__init__.py
aiodi/builder.py
aiodi/container.py
aiodi/helpers.py
aiodi/logger.py
aiodi/py.typed
aiodi/toml.py
aiodi/resolver/__init__.py
aiodi/resolver/loader.py
aiodi/resolver/path.py
aiodi/resolver/service.py
aiodi/resolver/variable.py
aiodi-1.3.0.dist-info/licenses/LICENSE
aiodi-1.3.0.dist-info/METADATA
aiodi-1.3.0.dist-info/WHEEL
aiodi-1.3.0.dist-info/top_level.txt
aiodi-1.3.0.dist-info/RECORD
